{
  "project_info": {
    "project_number": "915689449026",
    "project_id": "unieats-e62de",
    "storage_bucket": "unieats-e62de.appspot.com"
  },
  "client": [
    {
      "client_info": {
        "mobilesdk_app_id": "1:915689449026:android:8cf43bc721dba5829c6fdb",
        "android_client_info": {
          "package_name": "com.example.unieats"
        }
      },
      "oauth_client": [],
      "api_key": [
        {
          "current_key": "AIzaSyAA9CcHmJ4XR5dPC22idvSqPoQySsXcj8Y"
        }
      ],
      "services": {
        "appinvite_service": {
          "other_platform_oauth_client": []
        }
      }
    }
  ],
  "configuration_version": "1"
}